LICENSE
README.md
setup.cfg
setup.py
Plotter/Plotter.py
Plotter/__init__.py
easierplotlib.egg-info/PKG-INFO
easierplotlib.egg-info/SOURCES.txt
easierplotlib.egg-info/dependency_links.txt
easierplotlib.egg-info/not-zip-safe
easierplotlib.egg-info/requires.txt
easierplotlib.egg-info/top_level.txt