Metadata-Version: 2.1
Name: easierplotlib
Version: 0.2
Summary: Testing installation of Package
Home-page: UNKNOWN
Author: Zachary Davis
Author-email: zachkdavis00@gmail.com
License: MIT
Platform: UNKNOWN
License-File: LICENSE
